[
    {
        "IPO Name":"Avana Electrosystems",
        "Type_sub":"SME",
        "Day":"12-14 Jan",
        "QIB":0.0,
        "NII":0.0,
        "Retail":"0.00",
        "Total":0.0,
        "Normalized_IPO_Name":"Avana Electrosystems",
        "Stock \/ IPO":"Avana Electrosystems",
        "IPO GMP":4.5,
        "IPO Price":59.0,
        "Listing Gain":7.63,
        "Review":"Neutral",
        "Date":"12-14 Jan",
        "Type_gmp":"SME"
    },
    {
        "IPO Name":"GRE Renew Enertech",
        "Type_sub":"SME",
        "Day":"13-16 Jan",
        "QIB":0.0,
        "NII":0.0,
        "Retail":"0.00",
        "Total":0.0,
        "Normalized_IPO_Name":"GRE Renew Enertech",
        "Stock \/ IPO":"GRE Renew Enertech",
        "IPO GMP":9.0,
        "IPO Price":105.0,
        "Listing Gain":8.57,
        "Review":"Neutral",
        "Date":"13-16 Jan",
        "Type_gmp":"SME"
    },
    {
        "IPO Name":"Gabion Technologies",
        "Type_sub":"SME",
        "Day":"3",
        "QIB":9.97,
        "NII":516.11,
        "Retail":"367.62",
        "Total":297.49,
        "Normalized_IPO_Name":"Gabion Technologies",
        "Stock \/ IPO":"Gabion Technologies",
        "IPO GMP":30.0,
        "IPO Price":81.0,
        "Listing Gain":37.04,
        "Review":"May Apply",
        "Date":"6-8 Jan",
        "Type_gmp":"SME"
    },
    {
        "IPO Name":"INDO SMC",
        "Type_sub":"SME",
        "Day":"13-15 Jan",
        "QIB":0.0,
        "NII":0.0,
        "Retail":"0.00",
        "Total":0.0,
        "Normalized_IPO_Name":"INDO SMC",
        "Stock \/ IPO":"INDO SMC",
        "IPO GMP":25.0,
        "IPO Price":149.0,
        "Listing Gain":16.78,
        "Review":"Neutral",
        "Date":"13-15 Jan",
        "Type_gmp":"SME"
    },
    {
        "IPO Name":"Yajur Fibres",
        "Type_sub":"SME",
        "Day":"2",
        "QIB":1.03,
        "NII":0.8,
        "Retail":"1.14",
        "Total":1.04,
        "Normalized_IPO_Name":"Yajur Fibres",
        "Stock \/ IPO":"Yajur Fibres",
        "IPO GMP":15.0,
        "IPO Price":174.0,
        "Listing Gain":8.62,
        "Review":"May Apply",
        "Date":"7-9 Jan",
        "Type_gmp":"SME"
    }
]